<?xml version="1.0" encoding="UTF-8"?>
<calcwizard xmlns="xml.model.kalypso.org" 
	xmlns:xsi="http://www.w3.org/2001/XMLSchema-instance">

<!-- KONTROLLE DER ZEITREIHEN -->
<!-- Wasserstand / Abfluss -->
    <page className="org.kalypso.ui.calcwizard.modelpages.ObservationMapTableDiagWizardPage" pageTitle="Kontrolle Wasserstände - Eingabepegel" imageLocation="icons/calcwizard/kalypso32.gif" >
        <arg name="mapTemplate" value=".templates/Modell/Karten/Eingabepegel.gmt"/>

        <arg name="mainSash" value="50"/>
        <arg name="rightSash" value="50"/>
        <arg name="selectionID" value="2"/>
        <arg name="zmlTableShow" value="all"/>
        <arg name="timeserie1" value="diagDateAxis=d#diagValueAxis=w#nameColumn=Name#linkColumn=Ganglinie_gemessen"/>
    </page>
 
</calcwizard>